__init__.py
labcomm.py
labcomm-0.0.3.dist-info/LICENSE
labcomm-0.0.3.dist-info/METADATA
labcomm-0.0.3.dist-info/WHEEL
labcomm-0.0.3.dist-info/top_level.txt
labcomm-0.0.3.dist-info/RECORD
