Metadata-Version: 2.1
Name: labcomm
Version: 0.0.3
Summary: A fast binary protocol for interacting with integrated circuit demonstration boards.
Author-email: Steve Martin <Steve.Martin@analog.com>
Project-URL: Homepage, https://github.com/Xenomorphxx121/labcomm
Project-URL: Bug Tracker, https://github.com/Xenomorphxx121/labcomm/issues
Classifier: Programming Language :: Python :: 3
Classifier: License :: OSI Approved :: MIT License
Classifier: Operating System :: OS Independent
Requires-Python: >=3.7
License-File: LICENSE
